[{"line":1,"elements":[{"start_timestamp":"2023-11-28T02:52:55.942Z","line":5,"name":"verify user can successfully sign up","description":"","id":"this-feature-is-for-signup-functionality;verify-user-can-successfully-sign-up","type":"scenario","keyword":"Scenario","steps":[{"result":{"duration":537480700,"status":"passed"},"line":7,"name":"Launch \"<URL>\"","match":{"arguments":[{"val":"\"<URL>\"","offset":7}],"location":"stepDefinationTest3.Launchurl3.launch(java.lang.String)"},"keyword":"Given "},{"result":{"duration":3112485600,"status":"passed"},"line":8,"name":"user click signup link","match":{"location":"stepDefinationTest3.SignupTest3.user_click_signup_link()"},"keyword":"When "},{"result":{"duration":5260259100,"status":"passed"},"line":9,"name":"enter username, password and click signup button","match":{"location":"stepDefinationTest3.SignupTest3.enter_username_password_and_click_signup_button()"},"keyword":"And "},{"result":{"status":"passed"},"line":10,"name":"verify user can successfully signup","match":{"location":"stepDefinationTest3.SignupTest3.verify_user_can_successfully_signup()"},"keyword":"Then "}],"tags":[{"name":"@SignupTest3"}]}],"name":"This feature is for signup functionality","description":"","id":"this-feature-is-for-signup-functionality","keyword":"Feature","uri":"file:src/test/resources/FeatureFolderTest3/SignupTest3.feature","tags":[]}]